quickcache/__init__.py
quickcache/cache_helpers.py
quickcache/django_quickcache.py
quickcache/logger.py
quickcache/native_utc.py
quickcache/quickcache.py
quickcache/quickcache_helper.py
quickcache-0.5.4.dist-info/LICENSE
quickcache-0.5.4.dist-info/METADATA
quickcache-0.5.4.dist-info/WHEEL
quickcache-0.5.4.dist-info/top_level.txt
quickcache-0.5.4.dist-info/RECORD
