Metadata-Version: 2.1
Name: quickcache
Version: 0.5.4
Summary: caching has never been easier
Home-page: https://github.com/dimagi/quickcache
Author: Dimagi
Author-email: dev@dimagi.com
License: UNKNOWN
Platform: UNKNOWN
Classifier: Programming Language :: Python
Classifier: Programming Language :: Python :: 2
Classifier: Programming Language :: Python :: 2.7
Classifier: Programming Language :: Python :: 3
Classifier: Programming Language :: Python :: 3.5
Classifier: Programming Language :: Python :: 3.6
Requires-Dist: six
